netbox_services/__init__.py
netbox_services/filtersets.py
netbox_services/forms.py
netbox_services/models.py
netbox_services/navigation.py
netbox_services/tables.py
netbox_services/urls.py
netbox_services/views.py
netbox_services/api/__init__.py
netbox_services/api/serializers.py
netbox_services/api/urls.py
netbox_services/api/views.py
netbox_services/migrations/0001_initial.py
netbox_services/migrations/__init__.py
netbox_services/templates/netbox_services/service.html
netbox_services-0.0.10.dist-info/METADATA
netbox_services-0.0.10.dist-info/WHEEL
netbox_services-0.0.10.dist-info/top_level.txt
netbox_services-0.0.10.dist-info/RECORD
