Metadata-Version: 2.4
Name: netbox-services
Version: 0.0.10
Summary: A NetBox services Plugin for Service Providers
Author-email: Arturo Baldo <baldoarturo@gmail.com>
Maintainer-email: Arturo Baldo <baldoarturo@gmail.com>
Project-URL: Documentation, https://github.com/baldoarturo/netbox-services/blob/main/README.md
Project-URL: Source, https://github.com/baldoarturo/netbox-services
Project-URL: Tracker, https://github.com/baldoarturo/netbox-services/issues
Keywords: netbox-plugin
Classifier: Development Status :: 3 - Alpha
Classifier: Intended Audience :: Developers
Classifier: Natural Language :: English
Classifier: Programming Language :: Python :: 3 :: Only
Classifier: Programming Language :: Python :: 3.10
Classifier: Programming Language :: Python :: 3.11
Classifier: Programming Language :: Python :: 3.12
Requires-Python: >=3.10
